docipy/__init__.py
docipy/main.py
docipy/.system/imports.py
docipy/.system/index.py
docipy/.system/modules/-placeholder
docipy/.system/sources/author.png
docipy/.system/sources/bootstrap-icons.woff
docipy/.system/sources/bootstrap-icons.woff2
docipy/.system/sources/bootstrap.icons.css
docipy/.system/sources/clight.json
docipy/.system/sources/docipy.js
docipy/.system/sources/docipy.scss
docipy/.system/sources/highlight.js
docipy/.system/sources/logo.ico
docipy/.system/sources/robots.txt
docipy/.system/sources/sitemap.xml
docipy/.system/sources/template.html
docipy/.system/sources/lng/ge.yaml
docipy/.system/sources/lng/ru.yaml
docipy-2.1.1.dist-info/licenses/LICENSE
docipy-2.1.1.dist-info/METADATA
docipy-2.1.1.dist-info/WHEEL
docipy-2.1.1.dist-info/entry_points.txt
docipy-2.1.1.dist-info/top_level.txt
docipy-2.1.1.dist-info/RECORD
