Metadata-Version: 2.4
Name: docipy
Version: 2.1.1
Summary: DociPy is designed to easily generate impressive static HTML documentations
Home-page: https://github.com/IG-onGit/DociPy
Author: Irakli Gzirishvili
Author-email: gziraklirex@gmail.com
Classifier: Programming Language :: Python :: 3
Classifier: License :: OSI Approved :: MIT License
Classifier: Operating System :: OS Independent
License-File: LICENSE
Requires-Dist: clight
Requires-Dist: markdown
Dynamic: author
Dynamic: author-email
Dynamic: classifier
Dynamic: description
Dynamic: description-content-type
Dynamic: home-page
Dynamic: license-file
Dynamic: requires-dist
Dynamic: summary
